setup.py
antfarm/__init__.py
antfarm/base.py
antfarm/request.py
antfarm/response.py
antfarm.egg-info/PKG-INFO
antfarm.egg-info/SOURCES.txt
antfarm.egg-info/dependency_links.txt
antfarm.egg-info/not-zip-safe
antfarm.egg-info/top_level.txt
antfarm/utils/__init__.py
antfarm/utils/config.py
antfarm/utils/functional.py
antfarm/views/__init__.py
antfarm/views/static.py
antfarm/views/urls.py