Metadata-Version: 1.1
Name: antfarm
Version: 0.0.3
Summary: An ultra-light-weight web framework
Home-page: http://github.com/funkybob/antfarm
Author: Curtis Maloney
Author-email: curtis@tinbrain.net
License: UNKNOWN
Keywords: wsgi
Platform: UNKNOWN
Classifier: Environment :: Web Environment
Classifier: License :: OSI Approved :: MIT License
Classifier: Operating System :: OS Independent
Classifier: Programming Language :: Python
Classifier: Programming Language :: Python :: 3
